torch_utils/__init__.py
torch_utils/tensor_utils.py
pytorch_pytorchvision_utils-0.1.0.dist-info/LICENSE
pytorch_pytorchvision_utils-0.1.0.dist-info/METADATA
pytorch_pytorchvision_utils-0.1.0.dist-info/WHEEL
pytorch_pytorchvision_utils-0.1.0.dist-info/top_level.txt
pytorch_pytorchvision_utils-0.1.0.dist-info/RECORD
